AUTHORS
COPYING
LICENSE.TXT
MANIFEST.in
README.rst
setup.py
libMR/MetaRecognition.cpp
libMR/MetaRecognition.h
libMR/weibull.c
libMR/weibull.h
libmr.egg-info/PKG-INFO
libmr.egg-info/SOURCES.txt
libmr.egg-info/dependency_links.txt
libmr.egg-info/requires.txt
libmr.egg-info/top_level.txt
python/libmr.pyx