Metadata-Version: 1.0
Name: libmr
Version: 0.1.7
Summary: LibMR, the MetaRecognition library
Home-page: https://github.com/Vastlab/libMR
Author: Terry Boult, Ethan Rudd, and Manuel Gunther
Author-email: UNKNOWN
License: http://www.metarecognition.com/libmr-license/
Platform: UNKNOWN
